{
  "solarTerms": [
    {
      "name": "立春",
      "description": "立春是春季的第一个节气，此时太阳到达黄经315°。立，是开始的意思；春，代表着温暖、生长。立春意味着万物复苏的开始，新一年的农耕活动也由此开始。",
      "naturalSigns": [
        "东风解冻，散而为雨",
        "蛰虫始振，鱼陟负冰",
        "候雁北飞，草木萌动"
      ],
      "farmingTips": [
        "准备春耕工具",
        "选择适合早春种植的蔬菜",
        "整理菜园土壤"
      ]
    },
    {
      "name": "雨水",
      "description": "雨水是春季的第二个节气，此时太阳到达黄经330°。雨水表示降雨开始，雪渐消融，气温回升，雨量增加。'天一生水，春始属木，然生木者必水也，故立春后继之雨水。'",
      "naturalSigns": [
        "雨量渐增，冰雪消融",
        "鸣鸟始鸣，草木渐长",
        "田间湿度增加"
      ],
      "farmingTips": [
        "播种耐寒蔬菜",
        "注意排水防涝",
        "准备育苗温床"
      ]
    },
    {
      "name": "惊蛰",
      "description": "惊蛰是春季的第三个节气，此时太阳到达黄经345°。惊蛰表示天气回暖，春雷始鸣，惊醒了蛰伏在土中冬眠的昆虫。'惊者，动也；蛰者，藏也。'",
      "naturalSigns": [
        "春雷始鸣，惊醒蛰虫",
        "桃花始开，草木萌动",
        "蚯蚓出土，燕子北归"
      ],
      "farmingTips": [
        "开始春耕",
        "播种春季蔬菜",
        "注意病虫害防治"
      ]
    },
    {
      "name": "春分",
      "description": "春分是春季的第四个节气，此时太阳到达黄经0°。春分表示昼夜平分，阴阳相半，日照增长，气温升高。'分者半也，此当春之半。'",
      "naturalSigns": [
        "昼夜等长，阴阳平分",
        "桃花盛开，杏花初绽",
        "候鸟北迁，春雨绵绵"
      ],
      "farmingTips": [
        "播种主要农作物",
        "加强田间管理",
        "注意温度变化"
      ]
    },
    {
      "name": "清明",
      "description": "清明是春季的第五个节气，此时太阳到达黄经15°。清明表示天气晴朗，草木繁茂，万物生长。'清明者，万物皆洁齐而清明也。'",
      "naturalSigns": [
        "天气清爽，草木繁茂",
        "杏花盛开，梨花初绽",
        "燕子衔泥，筑巢安居"
      ],
      "farmingTips": [
        "播种喜温蔬菜",
        "注意防寒防旱",
        "施肥促进生长"
      ]
    },
    {
      "name": "谷雨",
      "description": "谷雨是春季的最后一个节气，此时太阳到达黄经30°。谷雨表示雨水充足，有利于谷类农作物生长。'雨生百谷，故名谷雨。'",
      "naturalSigns": [
        "雨量充沛，利于谷物生长",
        "牡丹花开，蚕开始育",
        "蛙声渐起，蜜蜂采花"
      ],
      "farmingTips": [
        "播种水稻",
        "加强田间管理",
        "注意防涝"
      ]
    },
    {
      "name": "立夏",
      "description": "立夏是夏季的第一个节气，此时太阳到达黄经45°。立夏表示夏季的开始，气温显著升高，雨水增多。'立夏，四立之一也，表示夏季开始。'",
      "naturalSigns": [
        "蝉始鸣，蚯蚓出",
        "王瓜生，苦菜秀",
        "鹿角解，蜜蜂飞"
      ],
      "farmingTips": [
        "种植夏季蔬菜",
        "注意防暑降温",
        "加强水分管理"
      ]
    },
    {
      "name": "小满",
      "description": "小满是夏季的第二个节气，此时太阳到达黄经60°。小满表示夏熟作物的籽粒开始饱满，但还未完全成熟。'小满者，物至于此小得盈满。'",
      "naturalSigns": [
        "苦菜花开，靡草枯死",
        "田间蛙鸣声渐起",
        "南风频繁，湿度增大"
      ],
      "farmingTips": [
        "加强田间管理",
        "注意防旱防涝",
        "防治病虫害"
      ]
    },
    {
      "name": "芒种",
      "description": "芒种是夏季的第三个节气，此时太阳到达黄经75°。芒种表示有芒的谷类作物可以种植或收获。'芒种者，有芒之谷可种也。'",
      "naturalSigns": [
        "麦收获，稻插秧",
        "蜜蜂采百花酿蜜",
        "蚕老柘枯，鹃始鸣"
      ],
      "farmingTips": [
        "收获冬小麦",
        "种植水稻",
        "注意防暑降温"
      ]
    },
    {
      "name": "夏至",
      "description": "夏至是夏季的第四个节气，此时太阳到达黄经90°。夏至表示北半球白昼时间最长，太阳直射点达到最北。'至，极也，日长之至，日影短至，故曰夏至。'",
      "naturalSigns": [
        "昼最长，夜最短",
        "蝉始鸣，半夏生",
        "温度最高，雨水充沛"
      ],
      "farmingTips": [
        "加强田间管理",
        "注意防暑降温",
        "防治病虫害"
      ]
    },
    {
      "name": "小暑",
      "description": "小暑是夏季的第五个节气，此时太阳到达黄经105°。小暑表示炎热的天气开始，但还未到最热。'暑，热也，就热之中分为大小，月初为小，月中为大，今则热气犹小也。'",
      "naturalSigns": [
        "温度升高，热浪来袭",
        "雷雨增多，湿度大",
        "蝉鸣加剧，知了声声"
      ],
      "farmingTips": [
        "加强田间管理",
        "注意防暑降温",
        "防治病虫害"
      ]
    },
    {
      "name": "大暑",
      "description": "大暑是夏季的最后一个节气，此时太阳到达黄经120°。大暑表示一年中最热的时期，常有暴雨。'大暑者，暑气最盛也。'",
      "naturalSigns": [
        "温度最高，热浪滚滚",
        "雷雨频繁，暴雨如注",
        "农作物生长最快"
      ],
      "farmingTips": [
        "加强田间管理",
        "注意防暑降温",
        "防治病虫害"
      ]
    },
    {
      "name": "立秋",
      "description": "立秋是秋季的第一个节气，此时太阳到达黄经135°。立秋表示秋季的开始，暑气渐退。'立秋，四立之一也，表示秋季开始。'",
      "naturalSigns": [
        "凉风至，白露降",
        "寒蝉鸣，鹰始击",
        "天气转凉，暑气渐消"
      ],
      "farmingTips": [
        "收获早稻",
        "种植秋季蔬菜",
        "注意防旱"
      ]
    },
    {
      "name": "处暑",
      "description": "处暑是秋季的第二个节气，此时太阳到达黄经150°。处暑表示炎热的天气结束，暑气消退。'处，止也，暑气至此而止矣。'",
      "naturalSigns": [
        "暑气消退，天高气爽",
        "禾乃登，鸿雁来",
        "天气渐凉，早晚温差大"
      ],
      "farmingTips": [
        "收获农作物",
        "种植秋季蔬菜",
        "注意防旱"
      ]
    },
    {
      "name": "白露",
      "description": "白露是秋季的第三个节气，此时太阳到达黄经165°。白露表示天气转凉，夜晚开始有露水。'阴气渐重，露凝而白也。'",
      "naturalSigns": [
        "露水凝结，草木染白",
        "鸿雁南飞，天气转凉",
        "早晚温差大，昼热夜凉"
      ],
      "farmingTips": [
        "收获农作物",
        "种植耐寒蔬菜",
        "注意防霜"
      ]
    },
    {
      "name": "秋分",
      "description": "秋分是秋季的第四个节气，此时太阳到达黄经180°。秋分表示昼夜平分，阴阳相半。'分者半也，此当秋之半。'",
      "naturalSigns": [
        "昼夜等长，阴阳平分",
        "雷始收声，蛰虫坯户",
        "天气转凉，露水增多"
      ],
      "farmingTips": [
        "收获农作物",
        "种植耐寒蔬菜",
        "注意防霜"
      ]
    },
    {
      "name": "寒露",
      "description": "寒露是秋季的第五个节气，此时太阳到达黄经195°。寒露表示天气更加寒冷，露水带有寒意。'寒露者，露气寒冷，将凝结也。'",
      "naturalSigns": [
        "露水带寒，草木渐枯",
        "鸿雁南飞，蛰虫入土",
        "天气寒冷，早晚温差大"
      ],
      "farmingTips": [
        "收获农作物",
        "种植耐寒蔬菜",
        "注意防霜"
      ]
    },
    {
      "name": "霜降",
      "description": "霜降是秋季的最后一个节气，此时太阳到达黄经210°。霜降表示天气寒冷，开始有霜。'霜降者，阴气凝重，露结为霜也。'",
      "naturalSigns": [
        "露凝为霜，草木黄落",
        "鸟兽归巢，蛰虫入土",
        "天气寒冷，早晚温差大"
      ],
      "farmingTips": [
        "收获农作物",
        "种植耐寒蔬菜",
        "注意防霜"
      ]
    },
    {
      "name": "立冬",
      "description": "立冬是冬季的第一个节气，此时太阳到达黄经225°。立冬表示冬季的开始，万物收藏。'立冬，四立之一也，表示冬季开始。'",
      "naturalSigns": [
        "水始冰，地始冻",
        "雉入大水为蜃，虹藏不见",
        "天气寒冷，草木凋零"
      ],
      "farmingTips": [
        "收获农作物",
        "种植耐寒蔬菜",
        "注意防寒"
      ]
    },
    {
      "name": "小雪",
      "description": "小雪是冬季的第二个节气，此时太阳到达黄经240°。小雪表示开始降雪，但雪量不大。'小雪者，雪未盛之辞也。'",
      "naturalSigns": [
        "天气寒冷，开始降雪",
        "鹖鴠不鸣，虎始交",
        "草木凋零，万物收藏"
      ],
      "farmingTips": [
        "收获农作物",
        "种植耐寒蔬菜",
        "注意防寒"
      ]
    },
    {
      "name": "大雪",
      "description": "大雪是冬季的第三个节气，此时太阳到达黄经255°。大雪表示降雪量增大。'大雪者，雪盛之辞也。'",
      "naturalSigns": [
        "天气严寒，降雪增多",
        "鹖鴠不鸣，虎始交",
        "草木凋零，万物收藏"
      ],
      "farmingTips": [
        "收获农作物",
        "种植耐寒蔬菜",
        "注意防寒"
      ]
    },
    {
      "name": "冬至",
      "description": "冬至是冬季的第四个节气，此时太阳到达黄经270°。冬至表示北半球白昼时间最短，太阳直射点达到最南。'至，极也，日短之至，日影长至，故曰冬至。'",
      "naturalSigns": [
        "昼最短，夜最长",
        "天气严寒，冰雪覆盖",
        "草木凋零，万物收藏"
      ],
      "farmingTips": [
        "收获农作物",
        "种植耐寒蔬菜",
        "注意防寒"
      ]
    },
    {
      "name": "小寒",
      "description": "小寒是冬季的第五个节气，此时太阳到达黄经285°。小寒表示天气寒冷，但还未到最冷。'寒，冷也，就冷之中分为大小，月初为小，月中为大，今则寒气犹小也。'",
      "naturalSigns": [
        "天气严寒，冰雪覆盖",
        "鹖鴠不鸣，虎始交",
        "草木凋零，万物收藏"
      ],
      "farmingTips": [
        "收获农作物",
        "种植耐寒蔬菜",
        "注意防寒"
      ]
    },
    {
      "name": "大寒",
      "description": "大寒是冬季的最后一个节气，此时太阳到达黄经300°。大寒表示一年中最冷的时期。'大寒者，寒气最盛也。'",
      "naturalSigns": [
        "天气最冷，冰雪覆盖",
        "鹖鴠不鸣，虎始交",
        "草木凋零，万物收藏"
      ],
      "farmingTips": [
        "收获农作物",
        "种植耐寒蔬菜",
        "注意防寒"
      ]
    }
  ]
}
